kraken/cli/__init__.py
kraken/cli/__main__.py
kraken/cli/buildenv/__init__.py
kraken/cli/buildenv/environment.py
kraken/cli/buildenv/inspect.py
kraken/cli/buildenv/lockfile.py
kraken/cli/buildenv/project.py
kraken/cli/buildenv/requirements.py
kraken/cli/commands/base.py
kraken/cli/commands/env.py
kraken/cli/commands/inspection.py
kraken/cli/commands/run.py
kraken/cli/py.typed
kraken_cli-0.2.9.dist-info/entry_points.txt
kraken_cli-0.2.9.dist-info/LICENSE
kraken_cli-0.2.9.dist-info/WHEEL
kraken_cli-0.2.9.dist-info/METADATA
kraken_cli-0.2.9.dist-info/RECORD
